aedificator/__init__.py
aedificator/_util.py
aedificator/main.py
aedificator/py.typed
aedificator/templates/Makefile.template
aedificator/templates/README.md.jinja
aedificator/templates/__init__.py.jinja
aedificator/templates/dot_dockerignore.template
aedificator/templates/dot_flake8.jinja
aedificator/templates/dot_gitignore.template
aedificator/templates/pyproject.toml.jinja
aedificator/templates/tox.ini.template
aedificator-2.1.0.dist-info/entry_points.txt
aedificator-2.1.0.dist-info/WHEEL
aedificator-2.1.0.dist-info/METADATA
aedificator-2.1.0.dist-info/RECORD
