Metadata-Version: 2.1
Name: aedificator
Version: 2.1.0
Summary: Aedificator - Python project scaffolding tool
Keywords: automation,scaffolding
Author-email: Libor Martinek <libasmartinek@protonmail.com>
Requires-Python: >=3.7
Classifier: Development Status :: 5 - Production/Stable
Classifier: Environment :: Console
Classifier: Intended Audience :: Developers
Classifier: Programming Language :: Python
Classifier: Programming Language :: Python :: 3.7
Classifier: Programming Language :: Python :: 3.8
Classifier: Programming Language :: Python :: 3.9
Classifier: Programming Language :: Python :: 3.10
Classifier: Programming Language :: Python :: 3 :: Only
Classifier: Topic :: Software Development :: Libraries :: Python Modules
Classifier: Topic :: Software Development :: Quality Assurance
Requires-Dist: Jinja2
Requires-Dist: click
Requires-Dist: tox ; extra == "dev"
Requires-Dist: flit ; extra == "dev"
Project-URL: Home, https://github.com/bibajz/aedificator
Provides-Extra: dev
